{
  "formatVersion": 1,
  "database": {
    "version": 7,
    "identityHash": "cebadea0163ad0bb8090958b993c2400",
    "entities": [
      {
        "tableName": "PlaybackStateEntity",
        "createSql": "CREATE TABLE IF NOT EXISTS `${TABLE_NAME}` (`mediaTitle` TEXT NOT NULL, `lastPosition` INTEGER NOT NULL, `playbackSpeed` REAL NOT NULL, `videoZoom` REAL NOT NULL, `sid` INTEGER NOT NULL, `secondarySid` INTEGER NOT NULL, `subDelay` INTEGER NOT NULL, `subSpeed` REAL NOT NULL, `aid` INTEGER NOT NULL, `audioDelay` INTEGER NOT NULL, `timeRemaining` INTEGER NOT NULL, `externalSubtitles` TEXT NOT NULL, PRIMARY KEY(`mediaTitle`))",
        "fields": [
          {
            "fieldPath": "mediaTitle",
            "columnName": "mediaTitle",
            "affinity": "TEXT",
            "notNull": true
          },
          {
            "fieldPath": "lastPosition",
            "columnName": "lastPosition",
            "affinity": "INTEGER",
            "notNull": true
          },
          {
            "fieldPath": "playbackSpeed",
            "columnName": "playbackSpeed",
            "affinity": "REAL",
            "notNull": true
          },
          {
            "fieldPath": "videoZoom",
            "columnName": "videoZoom",
            "affinity": "REAL",
            "notNull": true
          },
          {
            "fieldPath": "sid",
            "columnName": "sid",
            "affinity": "INTEGER",
            "notNull": true
          },
          {
            "fieldPath": "secondarySid",
            "columnName": "secondarySid",
            "affinity": "INTEGER",
            "notNull": true
          },
          {
            "fieldPath": "subDelay",
            "columnName": "subDelay",
            "affinity": "INTEGER",
            "notNull": true
          },
          {
            "fieldPath": "subSpeed",
            "columnName": "subSpeed",
            "affinity": "REAL",
            "notNull": true
          },
          {
            "fieldPath": "aid",
            "columnName": "aid",
            "affinity": "INTEGER",
            "notNull": true
          },
          {
            "fieldPath": "audioDelay",
            "columnName": "audioDelay",
            "affinity": "INTEGER",
            "notNull": true
          },
          {
            "fieldPath": "timeRemaining",
            "columnName": "timeRemaining",
            "affinity": "INTEGER",
            "notNull": true
          },
          {
            "fieldPath": "externalSubtitles",
            "columnName": "externalSubtitles",
            "affinity": "TEXT",
            "notNull": true
          }
        ],
        "primaryKey": {
          "autoGenerate": false,
          "columnNames": [
            "mediaTitle"
          ]
        }
      },
      {
        "tableName": "RecentlyPlayedEntity",
        "createSql": "CREATE TABLE IF NOT EXISTS `${TABLE_NAME}` (`id` INTEGER PRIMARY KEY AUTOINCREMENT NOT NULL, `filePath` TEXT NOT NULL, `fileName` TEXT NOT NULL, `videoTitle` TEXT, `duration` INTEGER NOT NULL, `fileSize` INTEGER NOT NULL, `width` INTEGER NOT NULL, `height` INTEGER NOT NULL, `timestamp` INTEGER NOT NULL, `launchSource` TEXT, `playlistId` INTEGER)",
        "fields": [
          {
            "fieldPath": "id",
            "columnName": "id",
            "affinity": "INTEGER",
            "notNull": true
          },
          {
            "fieldPath": "filePath",
            "columnName": "filePath",
            "affinity": "TEXT",
            "notNull": true
          },
          {
            "fieldPath": "fileName",
            "columnName": "fileName",
            "affinity": "TEXT",
            "notNull": true
          },
          {
            "fieldPath": "videoTitle",
            "columnName": "videoTitle",
            "affinity": "TEXT"
          },
          {
            "fieldPath": "duration",
            "columnName": "duration",
            "affinity": "INTEGER",
            "notNull": true
          },
          {
            "fieldPath": "fileSize",
            "columnName": "fileSize",
            "affinity": "INTEGER",
            "notNull": true
          },
          {
            "fieldPath": "width",
            "columnName": "width",
            "affinity": "INTEGER",
            "notNull": true
          },
          {
            "fieldPath": "height",
            "columnName": "height",
            "affinity": "INTEGER",
            "notNull": true
          },
          {
            "fieldPath": "timestamp",
            "columnName": "timestamp",
            "affinity": "INTEGER",
            "notNull": true
          },
          {
            "fieldPath": "launchSource",
            "columnName": "launchSource",
            "affinity": "TEXT"
          },
          {
            "fieldPath": "playlistId",
            "columnName": "playlistId",
            "affinity": "INTEGER"
          }
        ],
        "primaryKey": {
          "autoGenerate": true,
          "columnNames": [
            "id"
          ]
        }
      },
      {
        "tableName": "video_metadata_cache",
        "createSql": "CREATE TABLE IF NOT EXISTS `${TABLE_NAME}` (`path` TEXT NOT NULL, `size` INTEGER NOT NULL, `dateModified` INTEGER NOT NULL, `duration` INTEGER NOT NULL, `width` INTEGER NOT NULL, `height` INTEGER NOT NULL, `fps` REAL NOT NULL, `hasEmbeddedSubtitles` INTEGER NOT NULL, `subtitleCodec` TEXT NOT NULL, `lastScanned` INTEGER NOT NULL, PRIMARY KEY(`path`))",
        "fields": [
          {
            "fieldPath": "path",
            "columnName": "path",
            "affinity": "TEXT",
            "notNull": true
          },
          {
            "fieldPath": "size",
            "columnName": "size",
            "affinity": "INTEGER",
            "notNull": true
          },
          {
            "fieldPath": "dateModified",
            "columnName": "dateModified",
            "affinity": "INTEGER",
            "notNull": true
          },
          {
            "fieldPath": "duration",
            "columnName": "duration",
            "affinity": "INTEGER",
            "notNull": true
          },
          {
            "fieldPath": "width",
            "columnName": "width",
            "affinity": "INTEGER",
            "notNull": true
          },
          {
            "fieldPath": "height",
            "columnName": "height",
            "affinity": "INTEGER",
            "notNull": true
          },
          {
            "fieldPath": "fps",
            "columnName": "fps",
            "affinity": "REAL",
            "notNull": true
          },
          {
            "fieldPath": "hasEmbeddedSubtitles",
            "columnName": "hasEmbeddedSubtitles",
            "affinity": "INTEGER",
            "notNull": true
          },
          {
            "fieldPath": "subtitleCodec",
            "columnName": "subtitleCodec",
            "affinity": "TEXT",
            "notNull": true
          },
          {
            "fieldPath": "lastScanned",
            "columnName": "lastScanned",
            "affinity": "INTEGER",
            "notNull": true
          }
        ],
        "primaryKey": {
          "autoGenerate": false,
          "columnNames": [
            "path"
          ]
        }
      },
      {
        "tableName": "network_connections",
        "createSql": "CREATE TABLE IF NOT EXISTS `${TABLE_NAME}` (`id` INTEGER PRIMARY KEY AUTOINCREMENT NOT NULL, `name` TEXT NOT NULL, `protocol` TEXT NOT NULL, `host` TEXT NOT NULL, `port` INTEGER NOT NULL, `username` TEXT NOT NULL, `password` TEXT NOT NULL, `path` TEXT NOT NULL, `isAnonymous` INTEGER NOT NULL, `lastConnected` INTEGER NOT NULL, `autoConnect` INTEGER NOT NULL, `useHttps` INTEGER NOT NULL)",
        "fields": [
          {
            "fieldPath": "id",
            "columnName": "id",
            "affinity": "INTEGER",
            "notNull": true
          },
          {
            "fieldPath": "name",
            "columnName": "name",
            "affinity": "TEXT",
            "notNull": true
          },
          {
            "fieldPath": "protocol",
            "columnName": "protocol",
            "affinity": "TEXT",
            "notNull": true
          },
          {
            "fieldPath": "host",
            "columnName": "host",
            "affinity": "TEXT",
            "notNull": true
          },
          {
            "fieldPath": "port",
            "columnName": "port",
            "affinity": "INTEGER",
            "notNull": true
          },
          {
            "fieldPath": "username",
            "columnName": "username",
            "affinity": "TEXT",
            "notNull": true
          },
          {
            "fieldPath": "password",
            "columnName": "password",
            "affinity": "TEXT",
            "notNull": true
          },
          {
            "fieldPath": "path",
            "columnName": "path",
            "affinity": "TEXT",
            "notNull": true
          },
          {
            "fieldPath": "isAnonymous",
            "columnName": "isAnonymous",
            "affinity": "INTEGER",
            "notNull": true
          },
          {
            "fieldPath": "lastConnected",
            "columnName": "lastConnected",
            "affinity": "INTEGER",
            "notNull": true
          },
          {
            "fieldPath": "autoConnect",
            "columnName": "autoConnect",
            "affinity": "INTEGER",
            "notNull": true
          },
          {
            "fieldPath": "useHttps",
            "columnName": "useHttps",
            "affinity": "INTEGER",
            "notNull": true
          }
        ],
        "primaryKey": {
          "autoGenerate": true,
          "columnNames": [
            "id"
          ]
        }
      },
      {
        "tableName": "PlaylistEntity",
        "createSql": "CREATE TABLE IF NOT EXISTS `${TABLE_NAME}` (`id` INTEGER PRIMARY KEY AUTOINCREMENT NOT NULL, `name` TEXT NOT NULL, `createdAt` INTEGER NOT NULL, `updatedAt` INTEGER NOT NULL, `m3uSourceUrl` TEXT, `isM3uPlaylist` INTEGER NOT NULL)",
        "fields": [
          {
            "fieldPath": "id",
            "columnName": "id",
            "affinity": "INTEGER",
            "notNull": true
          },
          {
            "fieldPath": "name",
            "columnName": "name",
            "affinity": "TEXT",
            "notNull": true
          },
          {
            "fieldPath": "createdAt",
            "columnName": "createdAt",
            "affinity": "INTEGER",
            "notNull": true
          },
          {
            "fieldPath": "updatedAt",
            "columnName": "updatedAt",
            "affinity": "INTEGER",
            "notNull": true
          },
          {
            "fieldPath": "m3uSourceUrl",
            "columnName": "m3uSourceUrl",
            "affinity": "TEXT"
          },
          {
            "fieldPath": "isM3uPlaylist",
            "columnName": "isM3uPlaylist",
            "affinity": "INTEGER",
            "notNull": true
          }
        ],
        "primaryKey": {
          "autoGenerate": true,
          "columnNames": [
            "id"
          ]
        }
      },
      {
        "tableName": "PlaylistItemEntity",
        "createSql": "CREATE TABLE IF NOT EXISTS `${TABLE_NAME}` (`id` INTEGER PRIMARY KEY AUTOINCREMENT NOT NULL, `playlistId` INTEGER NOT NULL, `filePath` TEXT NOT NULL, `fileName` TEXT NOT NULL, `position` INTEGER NOT NULL, `addedAt` INTEGER NOT NULL, `lastPlayedAt` INTEGER NOT NULL, `playCount` INTEGER NOT NULL, `lastPosition` INTEGER NOT NULL, FOREIGN KEY(`playlistId`) REFERENCES `PlaylistEntity`(`id`) ON UPDATE NO ACTION ON DELETE CASCADE )",
        "fields": [
          {
            "fieldPath": "id",
            "columnName": "id",
            "affinity": "INTEGER",
            "notNull": true
          },
          {
            "fieldPath": "playlistId",
            "columnName": "playlistId",
            "affinity": "INTEGER",
            "notNull": true
          },
          {
            "fieldPath": "filePath",
            "columnName": "filePath",
            "affinity": "TEXT",
            "notNull": true
          },
          {
            "fieldPath": "fileName",
            "columnName": "fileName",
            "affinity": "TEXT",
            "notNull": true
          },
          {
            "fieldPath": "position",
            "columnName": "position",
            "affinity": "INTEGER",
            "notNull": true
          },
          {
            "fieldPath": "addedAt",
            "columnName": "addedAt",
            "affinity": "INTEGER",
            "notNull": true
          },
          {
            "fieldPath": "lastPlayedAt",
            "columnName": "lastPlayedAt",
            "affinity": "INTEGER",
            "notNull": true
          },
          {
            "fieldPath": "playCount",
            "columnName": "playCount",
            "affinity": "INTEGER",
            "notNull": true
          },
          {
            "fieldPath": "lastPosition",
            "columnName": "lastPosition",
            "affinity": "INTEGER",
            "notNull": true
          }
        ],
        "primaryKey": {
          "autoGenerate": true,
          "columnNames": [
            "id"
          ]
        },
        "indices": [
          {
            "name": "index_PlaylistItemEntity_playlistId",
            "unique": false,
            "columnNames": [
              "playlistId"
            ],
            "orders": [],
            "createSql": "CREATE INDEX IF NOT EXISTS `index_PlaylistItemEntity_playlistId` ON `${TABLE_NAME}` (`playlistId`)"
          }
        ],
        "foreignKeys": [
          {
            "table": "PlaylistEntity",
            "onDelete": "CASCADE",
            "onUpdate": "NO ACTION",
            "columns": [
              "playlistId"
            ],
            "referencedColumns": [
              "id"
            ]
          }
        ]
      }
    ],
    "setupQueries": [
      "CREATE TABLE IF NOT EXISTS room_master_table (id INTEGER PRIMARY KEY,identity_hash TEXT)",
      "INSERT OR REPLACE INTO room_master_table (id,identity_hash) VALUES(42, 'cebadea0163ad0bb8090958b993c2400')"
    ]
  }
}